adafruit_circuitpython_asyncio-3.0.3.dist-info/licenses/LICENSE
asyncio/__init__.py
asyncio/core.py
asyncio/event.py
asyncio/funcs.py
asyncio/lock.py
asyncio/stream.py
asyncio/task.py
asyncio/traceback.py
adafruit_circuitpython_asyncio-3.0.3.dist-info/METADATA
adafruit_circuitpython_asyncio-3.0.3.dist-info/WHEEL
adafruit_circuitpython_asyncio-3.0.3.dist-info/top_level.txt
adafruit_circuitpython_asyncio-3.0.3.dist-info/RECORD
