Metadata-Version: 2.4
Name: adafruit-circuitpython-asyncio
Version: 3.0.3
Summary: Cooperative multitasking and asynchronous I/O
Author-email: Adafruit Industries <circuitpython@adafruit.com>
License: MIT
Project-URL: Homepage, https://github.com/adafruit/Adafruit_CircuitPython_asyncio.git
Keywords: adafruit,blinka,circuitpython,micropython,asyncio,async
Classifier: Intended Audience :: Developers
Classifier: Topic :: Software Development :: Libraries
Classifier: Topic :: Software Development :: Embedded Systems
Classifier: Topic :: System :: Hardware
Classifier: License :: OSI Approved :: MIT License
Classifier: Programming Language :: Python :: 3
License-File: LICENSE
Requires-Dist: Adafruit-Blinka
Requires-Dist: adafruit-circuitpython-ticks
Provides-Extra: optional
Dynamic: license-file
